Metadata-Version: 2.1
Name: airflow-aws-executors
Version: 0.12
Summary: Apache Airflow Executor for AWS ECS, AWS Fargate, and AWS Batch
Home-page: https://github.com/aelzeiny/airflow-aws-executors
Author: Ahmed Elzeiny
Author-email: ahmed.elzeiny@gmail.com
License: MIT
Keywords: Apache,Airflow,AWS,Executor,Fargate,ECS,AWS ECS,AWS Batch,AWS Fargate
Platform: UNKNOWN
Classifier: License :: OSI Approved :: MIT License
Classifier: Programming Language :: Python :: 3
Classifier: Programming Language :: Python :: 3.6
Requires-Python: >=3.6.0
